progresslib/__init__.py
progresslib/cli.py
progresslib/gtk.py
progresslib-0.1.1.dist-info/LICENSE
progresslib-0.1.1.dist-info/METADATA
progresslib-0.1.1.dist-info/WHEEL
progresslib-0.1.1.dist-info/top_level.txt
progresslib-0.1.1.dist-info/RECORD
