Metadata-Version: 2.1
Name: progresslib
Version: 0.1.1
Summary: Various progressbars
Home-page: https://gitlab.com/pacholik1/ProgressLib
Author: Vojtěch Pachol
Author-email: pacholick@gmail.com
License: LGPL-3.0
Keywords: progressbar
Platform: UNKNOWN
Classifier: Development Status :: 4 - Beta
Classifier: Programming Language :: Python :: 3
License-File: LICENSE
Requires-Dist: colorama
